pythonslisp/Environment.py
pythonslisp/Lisp.py
pythonslisp/LispAST.py
pythonslisp/LispInterpreter.py
pythonslisp/LispParser.py
pythonslisp/Listener.py
pythonslisp/Parser.py
pythonslisp/__init__.py
pythonslisp/__main__.py
pythonslisp-0.19.0.dist-info/licenses/LICENSE
pythonslisp-0.19.0.dist-info/METADATA
pythonslisp-0.19.0.dist-info/WHEEL
pythonslisp-0.19.0.dist-info/top_level.txt
pythonslisp-0.19.0.dist-info/RECORD
