Metadata-Version: 2.4
Name: pythonslisp
Version: 0.19.0
Summary: A small Common Lisp implementation.  Call lisp and python from one another.
Author-email: Ronald H Provost/Longo <ronlongo9@outlook.com>
License-Expression: GPL-2.0-or-later
Project-URL: Homepage, https://github.com/rprovost11-sketch/Lisp
Project-URL: Issues, https://github.com/rprovost11-sketch/Lisp
Classifier: Programming Language :: Python :: 3
Classifier: Operating System :: OS Independent
Requires-Python: >=3.14
License-File: LICENSE
Dynamic: license-file
